mx_process_manager/__init__.py
mx_process_manager/__main__.py
mx_process_manager/formatter.py
mx_process_manager/manager.py
mx_process_manager/process_list.py
mx_process_manager/support.py
mx_process_manager/view_base.py
mx_process_manager/view_table.py
mx_process_manager/view_tree.py
mx_process_manager-1.0.3.dist-info/METADATA
mx_process_manager-1.0.3.dist-info/WHEEL
mx_process_manager-1.0.3.dist-info/entry_points.txt
mx_process_manager-1.0.3.dist-info/RECORD
