Metadata-Version: 2.3
Name: mx-process-manager
Version: 1.0.3
Summary: This is a tool that provides a GUI to manage processes and process trees.
Author: DarkLee
Author-email: darklee@tenonx.com
Requires-Python: >=3.12
Classifier: Programming Language :: Python :: 3
Classifier: Programming Language :: Python :: 3.12
Classifier: Programming Language :: Python :: 3.13
Requires-Dist: psutil (>=7.0.0,<8.0.0)
Requires-Dist: pyqt6 (>=6.9.1,<7.0.0)
